{"frames": {

"inventory.jpeg":
{
	"frame": {"x":0,"y":0,"w":192,"h":39},
	"rotated": false,
	"trimmed": false,
	"spriteSourceSize": {"x":0,"y":0,"w":192,"h":39},
	"sourceSize": {"w":192,"h":39}
},
"ok.png":
{
	"frame": {"x":192,"y":0,"w":1600,"h":1600},
	"rotated": false,
	"trimmed": false,
	"spriteSourceSize": {"x":0,"y":0,"w":1600,"h":1600},
	"sourceSize": {"w":1600,"h":1600}
}},
"meta": {
	"app": "http://www.codeandweb.com/texturepacker",
	"version": "1.0",
	"image": "util.png",
	"format": "RGBA8888",
	"size": {"w":1792,"h":1600},
	"scale": "1",
	"smartupdate": "$TexturePacker:SmartUpdate:7d11de94c9bda9fd1a84835680d6ee29:1da2cd0793b5d3cb803f46c894058a4f:ea51476c211b15ae76e4107c2ec467a4$"
}
}
