{"frames": {

"10.png":
{
	"frame": {"x":0,"y":0,"w":400,"h":400},
	"rotated": false,
	"trimmed": false,
	"spriteSourceSize": {"x":0,"y":0,"w":400,"h":400},
	"sourceSize": {"w":400,"h":400}
},
"11.png":
{
	"frame": {"x":400,"y":0,"w":400,"h":400},
	"rotated": false,
	"trimmed": false,
	"spriteSourceSize": {"x":0,"y":0,"w":400,"h":400},
	"sourceSize": {"w":400,"h":400}
},
"12.png":
{
	"frame": {"x":800,"y":0,"w":400,"h":400},
	"rotated": false,
	"trimmed": false,
	"spriteSourceSize": {"x":0,"y":0,"w":400,"h":400},
	"sourceSize": {"w":400,"h":400}
},
"20.png":
{
	"frame": {"x":1200,"y":0,"w":400,"h":400},
	"rotated": false,
	"trimmed": false,
	"spriteSourceSize": {"x":0,"y":0,"w":400,"h":400},
	"sourceSize": {"w":400,"h":400}
},
"21.png":
{
	"frame": {"x":0,"y":400,"w":400,"h":400},
	"rotated": false,
	"trimmed": false,
	"spriteSourceSize": {"x":0,"y":0,"w":400,"h":400},
	"sourceSize": {"w":400,"h":400}
},
"22.png":
{
	"frame": {"x":400,"y":400,"w":400,"h":400},
	"rotated": false,
	"trimmed": false,
	"spriteSourceSize": {"x":0,"y":0,"w":400,"h":400},
	"sourceSize": {"w":400,"h":400}
},
"30.png":
{
	"frame": {"x":800,"y":400,"w":400,"h":400},
	"rotated": false,
	"trimmed": false,
	"spriteSourceSize": {"x":0,"y":0,"w":400,"h":400},
	"sourceSize": {"w":400,"h":400}
},
"31.png":
{
	"frame": {"x":1200,"y":400,"w":400,"h":400},
	"rotated": false,
	"trimmed": false,
	"spriteSourceSize": {"x":0,"y":0,"w":400,"h":400},
	"sourceSize": {"w":400,"h":400}
},
"32.png":
{
	"frame": {"x":0,"y":800,"w":400,"h":400},
	"rotated": false,
	"trimmed": false,
	"spriteSourceSize": {"x":0,"y":0,"w":400,"h":400},
	"sourceSize": {"w":400,"h":400}
},
"40.png":
{
	"frame": {"x":400,"y":800,"w":400,"h":400},
	"rotated": false,
	"trimmed": false,
	"spriteSourceSize": {"x":0,"y":0,"w":400,"h":400},
	"sourceSize": {"w":400,"h":400}
},
"41.png":
{
	"frame": {"x":800,"y":800,"w":400,"h":400},
	"rotated": false,
	"trimmed": false,
	"spriteSourceSize": {"x":0,"y":0,"w":400,"h":400},
	"sourceSize": {"w":400,"h":400}
},
"42.png":
{
	"frame": {"x":1200,"y":800,"w":400,"h":400},
	"rotated": false,
	"trimmed": false,
	"spriteSourceSize": {"x":0,"y":0,"w":400,"h":400},
	"sourceSize": {"w":400,"h":400}
}},
"meta": {
	"app": "http://www.codeandweb.com/texturepacker",
	"version": "1.0",
	"image": "enemy.png",
	"format": "RGBA8888",
	"size": {"w":1600,"h":1200},
	"scale": "1",
	"smartupdate": "$TexturePacker:SmartUpdate:c18a0dc7ccd85e5354bf654cb7823b44:71c00fe1a8321eb280bd56a49a703f87:a99356c10d69482e9bee53d25c3d05e1$"
}
}
